ags/__init__.py
ags/base.py
ags/exceptions.py
ags/gp.py
ags/admin/__init__.py
ags/admin/paths.py
ags/admin/server.py
ags/admin/uploads.py
ags/admin/services/__init__.py
ags/admin/services/base.py
ags/admin/services/gp.py
ags/admin/services/mapserver.py
python_ags-0.3.2.dist-info/LICENSE
python_ags-0.3.2.dist-info/METADATA
python_ags-0.3.2.dist-info/WHEEL
python_ags-0.3.2.dist-info/top_level.txt
python_ags-0.3.2.dist-info/RECORD
