Metadata-Version: 2.1
Name: python-ags
Version: 0.3.2
Summary: A client interface to the REST API on ArcGIS Server 10.2.x
Home-page: https://bitbucket.org/databasin/python-ags
Author: Data Basin
Author-email: databasinadmin@consbio.org
Maintainer: Data Basin
Maintainer-email: databasinadmin@consbio.org
License: BSD
Keywords: arcgis ags
Platform: UNKNOWN
Requires: requests
